{
  "validate_on_submit": true,
  "show_errors_on_submit": false,
  "count": "1",
  "encounter_type": "PNC Follow Up",
  "entity_id": "",
  "relational_id": "",
  "metadata": {
    "start": {
      "openmrs_entity_parent": "",
      "openmrs_entity": "concept",
      "openmrs_data_type": "start",
      "openmrs_entity_id": "163137AAAAAAAAAAAAAAAAAAAAAAAAAAAAAA"
    },
    "end": {
      "openmrs_entity_parent": "",
      "openmrs_entity": "concept",
      "openmrs_data_type": "end",
      "openmrs_entity_id": "163138AAAAAAAAAAAAAAAAAAAAAAAAAAAAAA"
    },
    "today": {
      "openmrs_entity_parent": "",
      "openmrs_entity": "encounter",
      "openmrs_entity_id": "encounter_date"
    },
    "deviceid": {
      "openmrs_entity_parent": "",
      "openmrs_entity": "concept",
      "openmrs_data_type": "deviceid",
      "openmrs_entity_id": "163149AAAAAAAAAAAAAAAAAAAAAAAAAAAAAA"
    },
    "subscriberid": {
      "openmrs_entity_parent": "",
      "openmrs_entity": "concept",
      "openmrs_data_type": "subscriberid",
      "openmrs_entity_id": "163150AAAAAAAAAAAAAAAAAAAAAAAAAAAAAA"
    },
    "simserial": {
      "openmrs_entity_parent": "",
      "openmrs_entity": "concept",
      "openmrs_data_type": "simserial",
      "openmrs_entity_id": "163151AAAAAAAAAAAAAAAAAAAAAAAAAAAAAA"
    },
    "phonenumber": {
      "openmrs_entity_parent": "",
      "openmrs_entity": "concept",
      "openmrs_data_type": "phonenumber",
      "openmrs_entity_id": "163152AAAAAAAAAAAAAAAAAAAAAAAAAAAAAA"
    },
    "encounter_location": "",
    "look_up": {
      "entity_id": "",
      "value": ""
    }
  },
  "step1": {
    "title": "PNC Follow Up",
    "fields": [
      {
        "key": "contacted_chw",
        "openmrs_entity_parent": "",
        "openmrs_entity": "",
        "openmrs_entity_id": "",
        "openmrs_data_type": "",
        "type": "spinner",
        "hint": "Did you contact the CHW?",
        "values": [
          "Yes",
          "No"
        ]
      },
      {
        "key": "task_identity",
        "openmrs_entity_parent": "",
        "openmrs_entity": "concept",
        "openmrs_entity_id": "",
        "type": "hidden"
      }
    ]
  }
}